odoo/addons/partner_identification_unique_by_category/README.rst
odoo/addons/partner_identification_unique_by_category/__init__.py
odoo/addons/partner_identification_unique_by_category/__manifest__.py
odoo/addons/partner_identification_unique_by_category/i18n/partner_identification_unique_by_category.pot
odoo/addons/partner_identification_unique_by_category/models/__init__.py
odoo/addons/partner_identification_unique_by_category/models/res_partner_id_category.py
odoo/addons/partner_identification_unique_by_category/models/res_partner_id_number.py
odoo/addons/partner_identification_unique_by_category/readme/CONTRIBUTORS.rst
odoo/addons/partner_identification_unique_by_category/readme/DESCRIPTION.rst
odoo/addons/partner_identification_unique_by_category/static/description/icon.png
odoo/addons/partner_identification_unique_by_category/static/description/index.html
odoo/addons/partner_identification_unique_by_category/tests/__init__.py
odoo/addons/partner_identification_unique_by_category/tests/test_partner_identification_unique_by_category.py
odoo/addons/partner_identification_unique_by_category/views/res_partner_id_category_view.xml
odoo13_addon_partner_identification_unique_by_category-13.0.1.0.1.dev4.dist-info/METADATA
odoo13_addon_partner_identification_unique_by_category-13.0.1.0.1.dev4.dist-info/WHEEL
odoo13_addon_partner_identification_unique_by_category-13.0.1.0.1.dev4.dist-info/top_level.txt
odoo13_addon_partner_identification_unique_by_category-13.0.1.0.1.dev4.dist-info/RECORD
